aaaa/__init__.py
aaaa/main.py
aaaa-1.0.dist-info/LICENCE.txt
aaaa-1.0.dist-info/METADATA
aaaa-1.0.dist-info/WHEEL
aaaa-1.0.dist-info/top_level.txt
aaaa-1.0.dist-info/RECORD
