Metadata-Version: 2.1
Name: aaaa
Version: 1.0
Summary: Alphabetize output filenames
Home-page: http://github.com/sgrieve/aaaa
Author: Stuart WD Grieve
Author-email: stuart@swdg.io
License: MIT
Keywords: filenames,alphabetize
Platform: UNKNOWN
Classifier: Development Status :: 5 - Production/Stable
Classifier: License :: OSI Approved :: MIT License
Classifier: Programming Language :: Python :: 3
Classifier: Intended Audience :: Science/Research
Classifier: Intended Audience :: Developers
Classifier: Topic :: Scientific/Engineering
Classifier: Operating System :: OS Independent
